imitation_datasets/__init__.py
imitation_datasets/args.py
imitation_datasets/controller.py
imitation_datasets/experts.py
imitation_datasets/functions.py
imitation_datasets/utils.py
imitation_datasets/dataset/__init__.py
imitation_datasets/dataset/dataset.py
imitation_datasets/dataset/huggingface.py
imitation_datasets/dataset/metrics.py
imitation_datasets/dataset/random_dataset.py
imitation_datasets/register/__init__.py
imitation_datasets/register/atari.py
imitation_datasets/register/classic.py
imitation_datasets/register/mujoco.py
il_datasets-0.6.1.dist-info/LICENSE
il_datasets-0.6.1.dist-info/METADATA
il_datasets-0.6.1.dist-info/WHEEL
il_datasets-0.6.1.dist-info/top_level.txt
il_datasets-0.6.1.dist-info/RECORD
