Metadata-Version: 2.1
Name: il-datasets
Version: 0.6.1
Summary: A package for creating IL datasets
Home-page: https://github.com/NathanGavenski/IL-Datasets
Author: Nathan Gavenski
Author-email: nathangavenski@gmail.com
Classifier: Programming Language :: Python :: 3
Classifier: License :: OSI Approved :: MIT License
Classifier: Operating System :: OS Independent
Requires-Python: >=3.8.5
License-File: LICENSE
Requires-Dist: huggingface-sb3
Requires-Dist: stable-baselines3
Requires-Dist: sb3-contrib
Requires-Dist: tqdm
Requires-Dist: psutil
Requires-Dist: shimmy (>=0.2.1)
Requires-Dist: datasets
Requires-Dist: pandas
Provides-Extra: benchmark
Requires-Dist: torchvision ; extra == 'benchmark'
Requires-Dist: tensorboard-wrapper ; extra == 'benchmark'
Requires-Dist: tensorboard ; extra == 'benchmark'
Requires-Dist: tabulate ; extra == 'benchmark'
Requires-Dist: pyyaml ; extra == 'benchmark'
